jstprove-1.4.0.dist-info/licenses/LICENSE
python/__init__.py
python/core/__init__.py
python/core/binaries/__init__.py
python/core/binaries/expander-exec
python/core/binaries/onnx_generic_circuit_1-4-0
python/core/circuit_models/__init__.py
python/core/circuit_models/generic_onnx.py
python/core/circuit_models/simple_circuit.py
python/core/circuits/__init__.py
python/core/circuits/base.py
python/core/circuits/errors.py
python/core/circuits/zk_model_base.py
python/core/model_processing/__init__.py
python/core/model_processing/errors.py
python/core/model_processing/converters/__init__.py
python/core/model_processing/converters/base.py
python/core/model_processing/converters/onnx_converter.py
python/core/model_processing/onnx_custom_ops/__init__.py
python/core/model_processing/onnx_custom_ops/batchnorm.py
python/core/model_processing/onnx_custom_ops/conv.py
python/core/model_processing/onnx_custom_ops/custom_helpers.py
python/core/model_processing/onnx_custom_ops/gemm.py
python/core/model_processing/onnx_custom_ops/maxpool.py
python/core/model_processing/onnx_custom_ops/mul.py
python/core/model_processing/onnx_custom_ops/onnx_helpers.py
python/core/model_processing/onnx_custom_ops/relu.py
python/core/model_processing/onnx_quantizer/__init__.py
python/core/model_processing/onnx_quantizer/exceptions.py
python/core/model_processing/onnx_quantizer/onnx_op_quantizer.py
python/core/model_processing/onnx_quantizer/layers/__init__.py
python/core/model_processing/onnx_quantizer/layers/add.py
python/core/model_processing/onnx_quantizer/layers/base.py
python/core/model_processing/onnx_quantizer/layers/batchnorm.py
python/core/model_processing/onnx_quantizer/layers/clip.py
python/core/model_processing/onnx_quantizer/layers/constant.py
python/core/model_processing/onnx_quantizer/layers/conv.py
python/core/model_processing/onnx_quantizer/layers/gemm.py
python/core/model_processing/onnx_quantizer/layers/max.py
python/core/model_processing/onnx_quantizer/layers/maxpool.py
jstprove-1.4.0.dist-info/METADATA
jstprove-1.4.0.dist-info/WHEEL
jstprove-1.4.0.dist-info/entry_points.txt
jstprove-1.4.0.dist-info/top_level.txt
jstprove-1.4.0.dist-info/RECORD
