Metadata-Version: 2.4
Name: JSTprove
Version: 1.4.0
Summary: Zero-knowledge proofs of ML inference on ONNX models
Author: Inference Labs Inc
Requires-Python: >=3.10
License-File: LICENSE
Requires-Dist: numpy==2.2.6
Requires-Dist: onnx==1.17.0
Requires-Dist: onnxruntime==1.21.0
Requires-Dist: onnxruntime_extensions==0.14.0
Requires-Dist: psutil==7.0.0
Requires-Dist: Requests==2.32.3
Requires-Dist: scikit_learn==1.6.1
Requires-Dist: toml==0.10.2
Requires-Dist: tomli==2.0.1; python_version < "3.11"
Requires-Dist: torch==2.6.0
Requires-Dist: transformers==4.52.4
Dynamic: license-file
